blacktip/__init__.py
blacktip/angler.py
blacktip/old_angler_functions.py
blacktip/errors/__init__.py
blacktip/errors/errors.py
blacktip/form/__init__.py
blacktip/form/form.py
blacktip-0.0.9.dist-info/LICENSE
blacktip-0.0.9.dist-info/METADATA
blacktip-0.0.9.dist-info/WHEEL
blacktip-0.0.9.dist-info/top_level.txt
blacktip-0.0.9.dist-info/RECORD
