Metadata-Version: 2.1
Name: blacktip
Version: 0.0.9
Summary: SEC Edgar Analysis Tools (by Blacktip Research)
Home-page: https://mattbeveridge.com/blacktip-docs/
Author: Matt Beveridge
Author-email: mattjbev@gmail.com
License: MIT
Keywords: SEC,edgar,finance,10-K,10-Q,analytics
Platform: UNKNOWN
Classifier: Development Status :: 3 - Alpha
Classifier: Programming Language :: Python :: 3
Classifier: License :: OSI Approved :: MIT License
Classifier: Operating System :: OS Independent
Requires-Python: >=3.6
Requires-Dist: requests
Requires-Dist: pandas
Requires-Dist: sqlalchemy
Requires-Dist: pymysql
